{
  "checked_at": "2026-07-24T11:00:35Z",
  "sites": {
    "giveabit.io": {
      "status": "healthy",
      "http": "200",
      "latency": "0.142604"
    },
    "satohash.io": {
      "status": "healthy",
      "http": "200",
      "latency": "0.097493"
    },
    "hq.giveabit.io": {
      "status": "healthy",
      "http": "200",
      "latency": "0.105297"
    },
    "katoa.org": {
      "status": "healthy",
      "http": "200",
      "latency": "0.131514"
    },
    "tadbuy.giveabit.io": {
      "status": "healthy",
      "http": "200",
      "latency": "0.118131"
    },
    "stranded.giveabit.io": {
      "status": "healthy",
      "http": "200",
      "latency": "0.108590"
    },
    "motopass.giveabit.io": {
      "status": "healthy",
      "http": "200",
      "latency": "0.176986"
    },
    "sherpacarta.org": {
      "status": "healthy",
      "http": "200",
      "latency": "0.180486"
    },
    "openstrata.giveabit.io": {
      "status": "healthy",
      "http": "200",
      "latency": "0.228880"
    }
  },
  "site_issues": [],
  "cron_issues": [],
  "new_alerts": [],
  "summary": {
    "sites_healthy": 9,
    "sites_total": 9,
    "cron_failures": 0,
    "new_alerts": 0
  }
}