{
  "checked_at": "2026-07-23T21:06:51Z",
  "jobs": {
    "bb5980d548fb": {
      "status": "running",
      "last_run": null,
      "consecutive_fails": 0
    },
    "062cb12b5553": {
      "status": "completed",
      "last_run": "2026-07-23T02:00:45.015786+02:00",
      "consecutive_fails": 0
    },
    "12b477c661ae": {
      "status": "completed",
      "last_run": "2026-07-23T22:07:42.012044+02:00",
      "consecutive_fails": 0
    },
    "17029e4cdbed": {
      "status": "completed",
      "last_run": "2026-07-23T08:00:53.003487+02:00",
      "consecutive_fails": 0
    },
    "17affbe86a4e": {
      "status": "completed",
      "last_run": "2026-07-23T20:00:25.921230+02:00",
      "consecutive_fails": 0
    },
    "311d146f45c3": {
      "status": "completed",
      "last_run": "2026-07-23T07:15:49.899084+02:00",
      "consecutive_fails": 0
    },
    "337c7ae0b619": {
      "status": "completed",
      "last_run": "2026-07-23T07:30:57.332663+02:00",
      "consecutive_fails": 0
    },
    "42cdc3e9bd97": {
      "status": "completed",
      "last_run": "2026-07-23T23:04:00.431761+02:00",
      "consecutive_fails": 0
    },
    "44b42cec976a": {
      "status": "completed",
      "last_run": "2026-07-23T02:37:07.618219+02:00",
      "consecutive_fails": 0
    },
    "48e9ee316af5": {
      "status": "completed",
      "last_run": "2026-07-23T06:00:46.708367+02:00",
      "consecutive_fails": 0
    },
    "5c6f78744d6e": {
      "status": "completed",
      "last_run": "2026-07-23T07:00:50.848339+02:00",
      "consecutive_fails": 0
    },
    "7768b5c5aa49": {
      "status": "completed",
      "last_run": "2026-07-23T23:01:50.929970+02:00",
      "consecutive_fails": 0
    },
    "7e58d4dd29a7": {
      "status": "completed",
      "last_run": "2026-07-23T22:47:10.955885+02:00",
      "consecutive_fails": 0
    },
    "91d0082d0da5": {
      "status": "completed",
      "last_run": "2026-07-23T18:00:21.446099+02:00",
      "consecutive_fails": 0
    },
    "9bd2735e125e": {
      "status": "completed",
      "last_run": "2026-07-23T18:00:25.299603+02:00",
      "consecutive_fails": 0
    },
    "c8ce19bb5571": {
      "status": "completed",
      "last_run": "2026-07-23T23:05:32.509606+02:00",
      "consecutive_fails": 0
    },
    "cb8398b3fa67": {
      "status": "completed",
      "last_run": "2026-07-23T23:00:33.002077+02:00",
      "consecutive_fails": 0
    },
    "d62af99564f5": {
      "status": "completed",
      "last_run": "2026-07-23T23:03:25.908847+02:00",
      "consecutive_fails": 0
    },
    "d8c69ae4056e": {
      "status": "completed",
      "last_run": "2026-07-23T23:04:24.343197+02:00",
      "consecutive_fails": 0
    },
    "e8d5b97de501": {
      "status": "completed",
      "last_run": "2026-07-23T23:00:51.720877+02:00",
      "consecutive_fails": 0
    }
  },
  "paused_count": 0,
  "alert_count": 0
}